gemini_toolbox/__init__.py
gemini_toolbox/client.py
gemini_toolbox/declarations.py
gemini_toolbox/bin/__init__.py
gemini_toolbox/bin/pipe.py
gemini_toolbox/scheduler/__init__.py
gemini_toolbox/scheduler/task.py
gemini_toolbox-1.1.0.dist-info/METADATA
gemini_toolbox-1.1.0.dist-info/WHEEL
gemini_toolbox-1.1.0.dist-info/entry_points.txt
gemini_toolbox-1.1.0.dist-info/top_level.txt
gemini_toolbox-1.1.0.dist-info/RECORD
