Metadata-Version: 2.1
Name: gemini_toolbox
Version: 1.1.0
Summary: Toolbox For Using Gemini Agents SDK
Author: Viacheslav Kovalevskyi
Author-email: viacheslav@kovalevskyi.com
License: MIT
Requires-Dist: APScheduler ==3.10.4
Requires-Dist: google-cloud-storage ==2.18.2
Requires-Dist: google-generativeai ==0.7.2
Requires-Dist: python-dotenv ==1.0.1
